api_detail_modal.py
config_manager.py
container_registry_card_catalog.py
debug_console.py
info_modal.py
local_container_client.py
mock_data.py
registry_client.py
registry_config_modal.py
tag_detail_modal.py
tags_view.py
container_registry_card_catalog-0.0.0b1.dist-info/METADATA
container_registry_card_catalog-0.0.0b1.dist-info/WHEEL
container_registry_card_catalog-0.0.0b1.dist-info/entry_points.txt
container_registry_card_catalog-0.0.0b1.dist-info/licenses/LICENSE
container_registry_card_catalog-0.0.0b1.dist-info/licenses/LICENSE-VCL.md
container_registry_card_catalog-0.0.0b1.dist-info/RECORD
