Metadata-Version: 2.4
Name: container-registry-card-catalog
Version: 0.0.0b1
Summary: A Terminal User Interface for browsing container registries
Project-URL: Homepage, https://github.com/vibe-code-zone/container-registry-card-catalog
Project-URL: Repository, https://github.com/vibe-code-zone/container-registry-card-catalog
Project-URL: Issues, https://github.com/vibe-code-zone/container-registry-card-catalog/issues
Author-email: Andrew Potozniak <potozniak@redhat.com>
License: MIT License
License-File: LICENSE
License-File: LICENSE-VCL.md
Keywords: container,docker,podman,registry,terminal,tui
Classifier: Development Status :: 4 - Beta
Classifier: Environment :: Console
Classifier: Intended Audience :: Developers
Classifier: Operating System :: OS Independent
Classifier: Programming Language :: Python :: 3
Classifier: Programming Language :: Python :: 3.8
Classifier: Programming Language :: Python :: 3.9
Classifier: Programming Language :: Python :: 3.10
Classifier: Programming Language :: Python :: 3.11
Classifier: Programming Language :: Python :: 3.12
Classifier: Topic :: System :: Systems Administration
Classifier: Topic :: Utilities
Requires-Python: >=3.8
Requires-Dist: aiohttp>=3.8.0
Requires-Dist: httpx>=0.24.0
Requires-Dist: pyyaml>=6.0
Requires-Dist: textual>=0.41.0
